evtstrd/__init__.py
evtstrd/auth.py
evtstrd/cmdargs.py
evtstrd/config.py
evtstrd/date.py
evtstrd/dispatcher.py
evtstrd/events.py
evtstrd/exc.py
evtstrd/filters.py
evtstrd/http.py
evtstrd/http_server.py
evtstrd/listener.py
evtstrd/main.py
evtstrd/plugins/README.md
evtstrd/plugins/__init__.py
evtstrd/plugins/example_auth.py
evtstrd/server.py
evtstrd/socket_server.py
evtstrd/stats.py
evtstrd/util.py
evtstrd_test/__init__.py
evtstrd_test/date.py
evtstrd_test/events.py
evtstrd_test/filter.py
eventstreamd-2025.10.0.dist-info/METADATA
eventstreamd-2025.10.0.dist-info/WHEEL
eventstreamd-2025.10.0.dist-info/entry_points.txt
eventstreamd-2025.10.0.dist-info/licenses/LICENSE
eventstreamd-2025.10.0.dist-info/RECORD
