Metadata-Version: 2.4
Name: eventstreamd
Version: 2025.10.0
Summary: Simple Event Stream Server
License: MIT
License-File: LICENSE
Author: Sebastian Rittau
Author-email: srittau@rittau.biz
Requires-Python: >=3.10,<4.0
Classifier: Development Status :: 5 - Production/Stable
Classifier: License :: OSI Approved :: MIT License
Classifier: Programming Language :: Python :: 3
Classifier: Programming Language :: Python :: 3.10
Classifier: Programming Language :: Python :: 3.11
Classifier: Programming Language :: Python :: 3.12
Classifier: Programming Language :: Python :: 3.13
Classifier: Programming Language :: Python :: 3.14
Classifier: Topic :: Internet :: WWW/HTTP
Requires-Dist: json-get (>=1.1.1,<1.2.0)
Project-URL: Homepage, https://github.com/srittau/eventstreamd
Project-URL: Repository, https://github.com/srittau/eventstreamd
